xtrude/__init__.py
xtrude/xtrude.py
xtrude-0.1.2.dist-info/LICENSE
xtrude-0.1.2.dist-info/METADATA
xtrude-0.1.2.dist-info/WHEEL
xtrude-0.1.2.dist-info/top_level.txt
xtrude-0.1.2.dist-info/RECORD
