Metadata-Version: 2.1
Name: xtrude
Version: 0.1.2
Summary: An xarray extension for 3D terrain visualization
Home-page: https://github.com/davidbrochart/xtrude
Author: David Brochart
Author-email: david.brochart@gmail.com
License: MIT license
Keywords: xtrude
Platform: UNKNOWN
Classifier: Development Status :: 2 - Pre-Alpha
Classifier: Intended Audience :: Developers
Classifier: License :: OSI Approved :: MIT License
Classifier: Natural Language :: English
Classifier: Programming Language :: Python :: 3
Classifier: Programming Language :: Python :: 3.6
Classifier: Programming Language :: Python :: 3.7
Classifier: Programming Language :: Python :: 3.8
Classifier: Programming Language :: Python :: 3.9
Requires-Python: >=3.6
Requires-Dist: jupyter-server-proxy (>=1.5)
Requires-Dist: ipyspin (>=0.1.2)
Requires-Dist: rioxarray (>=0.1)
Requires-Dist: aiohttp (>=3)
Requires-Dist: aiohttp-cors (>=0.7)
Requires-Dist: pydeck (>=0.5)
Requires-Dist: mercantile (>=1)
Requires-Dist: affine (>=2)
Requires-Dist: pillow (>=7)
